AUTHORS.rst
CONTRIBUTING.rst
HISTORY.rst
LICENSE
MANIFEST.in
README.rst
setup.cfg
setup.py
docs/Makefile
docs/authors.rst
docs/conf.py
docs/contributing.rst
docs/history.rst
docs/index.rst
docs/installation.rst
docs/make.bat
docs/modules.rst
docs/readme.rst
docs/usage.rst
tests/__init__.py
tests/test_boards.py
tests/test_trellopy.py
trellopy/__init__.py
trellopy/backend.py
trellopy/boards.py
trellopy/members.py
trellopy/trellopy.py
trellopy.egg-info/PKG-INFO
trellopy.egg-info/SOURCES.txt
trellopy.egg-info/dependency_links.txt
trellopy.egg-info/not-zip-safe
trellopy.egg-info/pbr.json
trellopy.egg-info/requires.txt
trellopy.egg-info/top_level.txt