Metadata-Version: 1.1
Name: trellopy
Version: 0.0.0
Summary: A Python mockup of Trello with CLI
Home-page: https://github.com/mund/trellopy
Author: Amol Mundayoor
Author-email: amol.com@gmail.com
License: BSD
Keywords: trellopy
Platform: UNKNOWN
Classifier: Development Status :: 2 - Pre-Alpha
Classifier: Intended Audience :: Developers
Classifier: License :: OSI Approved :: BSD License
Classifier: Natural Language :: English
Classifier: Programming Language :: Python :: 2
Classifier: Programming Language :: Python :: 2.6
Classifier: Programming Language :: Python :: 2.7
Classifier: Programming Language :: Python :: 3
Classifier: Programming Language :: Python :: 3.3
Classifier: Programming Language :: Python :: 3.4
